intelmq_extensions/__init__.py
intelmq_extensions/bots/__init__.py
intelmq_extensions/bots/collectors/blackkite/__init__.py
intelmq_extensions/bots/collectors/blackkite/_client.py
intelmq_extensions/bots/collectors/blackkite/collector.py
intelmq_extensions/bots/collectors/disp/__init__.py
intelmq_extensions/bots/collectors/disp/_client.py
intelmq_extensions/bots/collectors/disp/collector.py
intelmq_extensions/bots/collectors/modat/__init__.py
intelmq_extensions/bots/collectors/modat/collector.py
intelmq_extensions/bots/collectors/xmpp/__init__.py
intelmq_extensions/bots/collectors/xmpp/collector.py
intelmq_extensions/bots/experts/__init__.py
intelmq_extensions/bots/experts/certat_contact_intern/__init__.py
intelmq_extensions/bots/experts/certat_contact_intern/expert.py
intelmq_extensions/bots/experts/copy_extra/__init__.py
intelmq_extensions/bots/experts/copy_extra/expert.py
intelmq_extensions/bots/experts/event_group_splitter/__init__.py
intelmq_extensions/bots/experts/event_group_splitter/expert.py
intelmq_extensions/bots/experts/event_splitter/__init__.py
intelmq_extensions/bots/experts/event_splitter/expert.py
intelmq_extensions/bots/experts/iban_extractor/__init__.py
intelmq_extensions/bots/experts/iban_extractor/expert.py
intelmq_extensions/bots/experts/replace_in_dict/__init__.py
intelmq_extensions/bots/experts/replace_in_dict/expert.py
intelmq_extensions/bots/experts/squelcher/__init__.py
intelmq_extensions/bots/experts/squelcher/expert.py
intelmq_extensions/bots/experts/vulnerability_lookup/__init__.py
intelmq_extensions/bots/experts/vulnerability_lookup/expert.py
intelmq_extensions/bots/outputs/__init__.py
intelmq_extensions/bots/outputs/mattermost/__init__.py
intelmq_extensions/bots/outputs/mattermost/output.py
intelmq_extensions/bots/outputs/to_logs/__init__.py
intelmq_extensions/bots/outputs/to_logs/output.py
intelmq_extensions/bots/outputs/xmpp/__init__.py
intelmq_extensions/bots/outputs/xmpp/output.py
intelmq_extensions/bots/parsers/__init__.py
intelmq_extensions-1.11.1.dist-info/licenses/LICENSE
intelmq_extensions-1.11.1.dist-info/METADATA
intelmq_extensions-1.11.1.dist-info/WHEEL
intelmq_extensions-1.11.1.dist-info/entry_points.txt
intelmq_extensions-1.11.1.dist-info/top_level.txt
intelmq_extensions-1.11.1.dist-info/RECORD
