Metadata-Version: 2.4
Name: intelmq_extensions
Version: 1.11.1
Summary: Additional bots for IntelMQ
Author: CERT.at Data & Development Team
License: AGPLv3
Project-URL: Repository, https://github.com/certat/intelmq-extensions
Classifier: Programming Language :: Python :: 3
Requires-Python: >=3.10
License-File: LICENSE
Requires-Dist: intelmq
Requires-Dist: python-termstyle>=0.1.10
Requires-Dist: rt<3.0.0,>=1.0.9
Requires-Dist: netaddr>=0.7.14
Requires-Dist: schwifty
Requires-Dist: mergedeep
Requires-Dist: psycopg2-binary
Requires-Dist: tabulate>=0.7.5
Requires-Dist: importlib_metadata; python_version < "3.8"
Provides-Extra: dev
Requires-Dist: pytest; extra == "dev"
Requires-Dist: tox>=4; extra == "dev"
Requires-Dist: ruff; extra == "dev"
Requires-Dist: isort; extra == "dev"
Requires-Dist: flake8; extra == "dev"
Requires-Dist: requests-mock; extra == "dev"
Requires-Dist: freezegun; extra == "dev"
Dynamic: license-file
Dynamic: requires-dist
